lumaconf/__init__.py
lumaconf/config_parser.py
lumaconf/config_tree.py
lumaconf/converter.py
lumaconf/exceptions.py
lumaconf/luma.py
lumaconf/period_parser.py
lumaconf/period_serializer.py
lumaconf/tool.py
lumaconf-0.0.2.dist-info/LICENSE
lumaconf-0.0.2.dist-info/METADATA
lumaconf-0.0.2.dist-info/WHEEL
lumaconf-0.0.2.dist-info/entry_points.txt
lumaconf-0.0.2.dist-info/top_level.txt
lumaconf-0.0.2.dist-info/RECORD
